zzsuki_test/__init__.py
zzsuki_test/core/__init__.py
zzsuki_test/core/data_driver.py
zzsuki_test/core/parameterized.py
zzsuki_test/core/re_run.py
zzsuki_test/core/result_push.py
zzsuki_test/core/send_email.py
zzsuki_test/core/test_result.py
zzsuki_test/core/test_runner.py
zzsuki_test/templates/__init__.py
zzsuki_test/templates/dingtalk.md
zzsuki_test/templates/templates.html
zzsuki_test/templates/templates03.html
zzsuki_test/templates/templates2.html
zzsuki_test/templates/templates3.html
zzsukitest-1.0.6.dist-info/METADATA
zzsukitest-1.0.6.dist-info/WHEEL
zzsukitest-1.0.6.dist-info/top_level.txt
zzsukitest-1.0.6.dist-info/RECORD
