Metadata-Version: 2.1
Name: zzsukitest
Version: 1.0.6
Summary: test runner for automation
Home-page: https://gitee.com/he_weidong/zzsuki_tests
Author: zzsuki
Author-email: zzsuki@163.com
License: UNKNOWN
Platform: UNKNOWN
Classifier: Programming Language :: Python :: 3
Classifier: License :: OSI Approved :: MIT License
Classifier: Operating System :: OS Independent
Requires-Python: >=3.6
Requires-Dist: Jinja2
Requires-Dist: PyYAML
Requires-Dist: requests
